pyANOVAapprox/__init__.py
pyANOVAapprox/analysis.py
pyANOVAapprox/approx.py
pyANOVAapprox/errors.py
pyANOVAapprox/fista.py
pyANOVAapprox/trafos.py
pyanovaapprox-1.0.0.dist-info/METADATA
pyanovaapprox-1.0.0.dist-info/WHEEL
pyanovaapprox-1.0.0.dist-info/licenses/LICENSE
pyanovaapprox-1.0.0.dist-info/RECORD
