Metadata-Version: 2.4
Name: pyANOVAapprox
Version: 1.0.0
Summary: Approximation Package for High-Dimensional Functions
Project-URL: Homepage, https://github.com/NFFT/pyGroupedTransforms
Author-email: Felix Wirth <fwi012001@gmail.com>
Maintainer-email: Pascal Schröter <pascal.schroeter@mathematik.tu-chemnitz.de>
License-File: LICENSE
Requires-Python: >=3.9
Requires-Dist: numpy>=2.0.0
Requires-Dist: pygroupedtransforms>=0.1.0
Requires-Dist: scipy>=1.16.0
